engora/__init__.py
engora/command_line.py
engora-1.3.0.dist-info/DESCRIPTION.rst
engora-1.3.0.dist-info/METADATA
engora-1.3.0.dist-info/RECORD
engora-1.3.0.dist-info/WHEEL
engora-1.3.0.dist-info/entry_points.txt
engora-1.3.0.dist-info/metadata.json
engora-1.3.0.dist-info/top_level.txt
