Metadata-Version: 2.0
Name: engora
Version: 1.3.0
Summary: Python client library for engora.tech
Home-page: https://engora.tech
Author: engora.tech
Author-email: dsa@engora.tech
License: MIT
Platform: UNKNOWN
Classifier: Programming Language :: Python :: 3
Classifier: License :: OSI Approved :: MIT License
Classifier: Operating System :: OS Independent
Requires-Dist: pint
Requires-Dist: requests
